common/__init__.py
common/common.py
backtests_common-0.0.1.dist-info/LICENSE
backtests_common-0.0.1.dist-info/WHEEL
backtests_common-0.0.1.dist-info/METADATA
backtests_common-0.0.1.dist-info/RECORD
